qcqp/__init__.py
qcqp/coeff_extractor.py
qcqp/qcqp.py
qcqp/settings.py
qcqp/utilities.py
qcqp-0.8.3.dist-info/METADATA
qcqp-0.8.3.dist-info/RECORD
qcqp-0.8.3.dist-info/WHEEL
qcqp-0.8.3.dist-info/top_level.txt
